mediapyr/__init__.py
mediapyr/mediator.py
mediapyr/py.typed
mediapyr-0.1.6.dist-info/licenses/LICENSE
mediapyr-0.1.6.dist-info/METADATA
mediapyr-0.1.6.dist-info/WHEEL
mediapyr-0.1.6.dist-info/top_level.txt
mediapyr-0.1.6.dist-info/RECORD
