Metadata-Version: 2.4
Name: mediapyr
Version: 0.1.6
Summary: Lightweight Mediator pattern (sync/async) for Python
Author-email: Nguyễn Tùng Sk <skfreelancer2004@gmail.com>
License: MIT License
Classifier: Programming Language :: Python :: 3
Classifier: Operating System :: OS Independent
Requires-Python: >=3.9
License-File: LICENSE
Dynamic: license-file
